[
    {
        "id": "EF1CC5BB-4785-4D8E-AB98-5FA4E00B6A61",
        "name": "Todd Myers",
        "Location": "Location test1",
        "Room": 34,
        "Diagnosis1": "Arthritis",
        "Restrictions": ["D", "S"],
        "Physician": "Physician",
        "CC": "CC test1",
        "HPI": "HPI test1",
        "MedHx": "MedHx test1",
        "SurgHx": "SurgHx1",
        "SocHx": "SocHx1",
        "FamHx": "FamHx1",
        "ROS": "ROS1",
        "Allergies": "Allergies1",
        "Medications": "Medications1",
        "Vaccinations": "Vaccinations1",
        "PE": "PE1",
        "Assess": "Assess1",
        "Plan": "Plan1"
    },
    {
        "id": "EF1CC5BB-4785-4D8E-AB98-5FA4E00B6A62",
        "name": "Wendy Myers",
        "Location": "Location test2",
        "Room": 4,
        "Diagnosis1": "Alzeimer's Dementia",
        "Restrictions": ["A", "S"],
        "Physician": "Physician2",
        "CC": "CC test2",
        "HPI": "HPI test2",
        "MedHx": "MedHx test2",
        "SurgHx": "SurgHx2",
        "SocHx": "SocHx2",
        "FamHx": "FamHx2",
        "ROS": "ROS2",
        "Allergies": "Allergies2",
        "Medications": "Medications2",
        "Vaccinations": "Vaccinations2",
        "PE": "PE2",
        "Assess": "Assess2",
        "Plan": "Plan2"
    },
    {
        "id": "EF1CC5BB-4785-4D8E-AB98-5FA4E00B6A63",
        "name": "Maddie Riley",
        "Location": "Location test3",
        "Room": 16,
        "Diagnosis1": "Arthritis, Chronic kidney failure, Hypertension",
        "Restrictions": ["D", "S", "A"],
        "Physician": "Physician3",
        "CC": "CC test3",
        "HPI": "HPI test3",
        "MedHx": "MedHx test3",
        "SurgHx": "SurgHx3",
        "SocHx": "SocHx3",
        "FamHx": "FamHx3",
        "ROS": "ROS3",
        "Allergies": "Allergies3",
        "Medications": "Medications3",
        "Vaccinations": "Vaccinations3",
        "PE": "PE3",
        "Assess": "Assess3",
        "Plan": "Plan3"
    },
    {
        "id": "EF1CC5BB-4785-4D8E-AB98-5FA4E00B6A64",
        "name": "Daffy Duck",
        "Location": "Location test4",
        "Room": 12,
        "Diagnosis1": "Bladder cancer",
        "Restrictions": ["D", "S"],
        "Physician": "Physician4",
        "CC": "CC test4",
        "HPI": "HPI test4",
        "MedHx": "MedHx test4",
        "SurgHx": "SurgHx4",
        "SocHx": "SocHx4",
        "FamHx": "FamHx4",
        "ROS": "ROS4",
        "Allergies": "Allergies4",
        "Medications": "Medications4",
        "Vaccinations": "Vaccinations4",
        "PE": "PE4",
        "Assess": "Assess4",
        "Plan": "Plan4"
    },
    {
        "id": "EF1CC5BB-4785-4D8E-AB98-5FA4E00B6A65",
        "name": "Bugs Bunny",
        "Location": "Location test5",
        "Room": 1,
        "Diagnosis1": "Migraine head aches",
        "Restrictions": ["D"],
        "Physician": "Physician5",
        "CC": "CC test5",
        "HPI": "HPI test5",
        "MedHx": "MedHx test5",
        "SurgHx": "SurgHx5",
        "SocHx": "SocHx5",
        "FamHx": "FamHx5",
        "ROS": "ROS5",
        "Allergies": "Allergies5",
        "Medications": "Medications5",
        "Vaccinations": "Vaccinations5",
        "PE": "PE5",
        "Assess": "Assess5",
        "Plan": "Plan5"
    }
]

